ezface/__init__.py
ezface/exceptions.py
ezface/my_snowflake.py
my_snowflake-0.0.1.dist-info/METADATA
my_snowflake-0.0.1.dist-info/WHEEL
my_snowflake-0.0.1.dist-info/top_level.txt
my_snowflake-0.0.1.dist-info/RECORD
