Metadata-Version: 2.1
Name: my-snowflake
Version: 0.0.1
Summary: This project provides a simple way to use the snowflake algorithm
Home-page: https://gitee.com/one-person-line/my_snowflake_package.git
Author: YunTing
Author-email: 3336160458@qq.com
